{"sentences": ["Wrangler : Anatomy of an Icon is a 2008 feature documentary film about the life of Jack Wrangler , produced and directed by Jeffrey Schwarz of Automat Pictures .\n", "It had its premiere at the 2008 New York Lesbian , Gay , Bisexual , & Transgender Film Festival ( Newfest ) and is distributed by TLA Releasing .\n", "The documentary chronicles the life of Jack Wrangler , the professional name of John Robert Stillman in his role as a gay porn star who rapidly became one of the first performers in gay porn to achieve star status and a cult following .\n", "The documentary also features his transitioning to roles such as straight porn star , his romantic relationship with and later marriage to singer Margaret Whiting , his activism in supporting and promoting AIDS charities and his later career as a theatrical producer and director .\n", "The documentary won a GayVNAward in 2009 for Best Alternative Release .\n", "Wrangler died on April 7 , 2009 at the age of 62 due to emphysema .\n"], "toktext": [[["Wrangler", "Wrangler"], [":", ":"], ["Anatomy", "anatomy"], ["of", "of"], ["an", "a"], ["Icon", "icon"], ["is", "be"], ["a", "a"], ["2008", "2008"], ["feature", "feature"], ["documentary", "documentary"], ["film", "film"], ["about", "about"], ["the", "the"], ["life", "life"], ["of", "of"], ["Jack", "Jack"], ["Wrangler", "Wrangler"], [",", ","], ["produced", "produce"], ["and", "and"], ["directed", "direct"], ["by", "by"], ["Jeffrey", "Jeffrey"], ["Schwarz", "Schwarz"], ["of", "of"], ["Automat", "Automat"], ["Pictures", "Pictures"], [".", "."]], [["It", "it"], ["had", "have"], ["its", "its"], ["premiere", "premiere"], ["at", "at"], ["the", "the"], ["2008", "2008"], ["New", "New"], ["York", "York"], ["Lesbian", "Lesbian"], [",", ","], ["Gay", "Gay"], [",", ","], ["Bisexual", "Bisexual"], [",", ","], ["&", "&"], ["Transgender", "Transgender"], ["Film", "Film"], ["Festival", "Festival"], ["(", "("], ["Newfest", "Newfest"], [")", ")"], ["and", "and"], ["is", "be"], ["distributed", "distribute"], ["by", "by"], ["TLA", "TLA"], ["Releasing", "release"], [".", "."]], [["The", "the"], ["documentary", "documentary"], ["chronicles", "chronicle"], ["the", "the"], ["life", "life"], ["of", "of"], ["Jack", "Jack"], ["Wrangler", "Wrangler"], [",", ","], ["the", "the"], ["professional", "professional"], ["name", "name"], ["of", "of"], ["John", "John"], ["Robert", "Robert"], ["Stillman", "Stillman"], ["in", "in"], ["his", "he"], ["role", "role"], ["as", "as"], ["a", "a"], ["gay", "gay"], ["porn", "porn"], ["star", "star"], ["who", "who"], ["rapidly", "rapidly"], ["became", "become"], ["one", "one"], ["of", "of"], ["the", "the"], ["first", "first"], ["performers", "performer"], ["in", "in"], ["gay", "gay"], ["porn", "porn"], ["to", "to"], ["achieve", "achieve"], ["star", "star"], ["status", "status"], ["and", "and"], ["a", "a"], ["cult", "cult"], ["following", "follow"], [".", "."]], [["The", "the"], ["documentary", "documentary"], ["also", "also"], ["features", "feature"], ["his", "he"], ["transitioning", "transition"], ["to", "to"], ["roles", "role"], ["such", "such"], ["as", "as"], ["straight", "straight"], ["porn", "porn"], ["star", "star"], [",", ","], ["his", "he"], ["romantic", "romantic"], ["relationship", "relationship"], ["with", "with"], ["and", "and"], ["later", "later"], ["marriage", "marriage"], ["to", "to"], ["singer", "singer"], ["Margaret", "Margaret"], ["Whiting", "Whiting"], [",", ","], ["his", "he"], ["activism", "activism"], ["in", "in"], ["supporting", "support"], ["and", "and"], ["promoting", "promote"], ["AIDS", "AIDS"], ["charities", "charity"], ["and", "and"], ["his", "he"], ["later", "later"], ["career", "career"], ["as", "as"], ["a", "a"], ["theatrical", "theatrical"], ["producer", "producer"], ["and", "and"], ["director", "director"], [".", "."]], [["The", "the"], ["documentary", "documentary"], ["won", "win"], ["a", "a"], ["GayVNAward", "GayVNAward"], ["in", "in"], ["2009", "2009"], ["for", "for"], ["Best", "good"], ["Alternative", "alternative"], ["Release", "release"], [".", "."]], [["Wrangler", "Wrangler"], ["died", "die"], ["on", "on"], ["April", "April"], ["7", "7"], [",", ","], ["2009", "2009"], ["at", "at"], ["the", "the"], ["age", "age"], ["of", "of"], ["62", "62"], ["due", "due"], ["to", "to"], ["emphysema", "emphysema"], [".", "."]]], "constit": ["(ROOT\n  (FRAG\n    (NP (NNP Wrangler))\n    (: :)\n    (S\n      (NP\n        (NP (NN Anatomy))\n        (PP (IN of)\n          (NP (DT an) (NN Icon))))\n      (VP\n        (VP (VBZ is)\n          (NP\n            (NP (DT a) (CD 2008) (NN feature) (NN documentary) (NN film))\n            (PP (IN about)\n              (NP\n                (NP (DT the) (NN life))\n                (PP (IN of)\n                  (NP (NNP Jack) (NNP Wrangler)))))))\n        (, ,)\n        (VP (VBD produced))\n        (CC and)\n        (VP (VBN directed)\n          (PP (IN by)\n            (NP\n              (NP (NNP Jeffrey) (NNP Schwarz))\n              (PP (IN of)\n                (NP (NNP Automat) (NNP Pictures))))))))\n    (. .)))\n", "(ROOT\n  (S\n    (NP (PRP It))\n    (VP\n      (VP (VBD had)\n        (NP\n          (NP\n            (NP (PRP$ its) (NN premiere))\n            (PP (IN at)\n              (NP (DT the) (CD 2008)\n                (NML\n                  (NML (NNP New) (NNP York) (NNP Lesbian))\n                  (, ,)\n                  (NP (NNP Gay))\n                  (, ,))\n                (NNP Bisexual))))\n          (, ,)\n          (CC &)\n          (NP\n            (NP (NNP Transgender) (NNP Film) (NNP Festival))\n            (NP (-LRB- -LRB-) (NNP Newfest) (-RRB- -RRB-)))))\n      (CC and)\n      (VP (VBZ is)\n        (VP (VBN distributed)\n          (PP (IN by)\n            (NP\n              (NP (NNP TLA))\n              (VP (VBG Releasing)))))))\n    (. .)))\n", "(ROOT\n  (S\n    (NP (DT The) (NN documentary))\n    (VP (VBZ chronicles)\n      (NP\n        (NP (DT the) (NN life))\n        (PP (IN of)\n          (NP\n            (NP (NNP Jack) (NNP Wrangler))\n            (, ,)\n            (NP\n              (NP (DT the) (JJ professional) (NN name))\n              (PP (IN of)\n                (NP\n                  (NP (NNP John) (NNP Robert) (NNP Stillman))\n                  (PP (IN in)\n                    (NP (PRP$ his) (NN role)))))))))\n      (PP (IN as)\n        (NP\n          (NP (DT a) (JJ gay) (NN porn) (NN star))\n          (SBAR\n            (WHNP (WP who))\n            (S\n              (ADVP (RB rapidly))\n              (VP (VBD became)\n                (NP\n                  (NP (CD one))\n                  (PP (IN of)\n                    (NP\n                      (NP (DT the) (JJ first) (NNS performers))\n                      (PP (IN in)\n                        (NP (JJ gay) (NN porn))))))\n                (S\n                  (VP (TO to)\n                    (VP (VB achieve)\n                      (NP\n                        (NP (NN star) (NN status))\n                        (CC and)\n                        (NP (DT a) (NN cult) (VBG following))))))))))))\n    (. .)))\n", "(ROOT\n  (S\n    (NP (DT The) (NN documentary))\n    (ADVP (RB also))\n    (VP\n      (VP (VBZ features)\n        (NP (PRP$ his) (VBG transitioning))\n        (PP (IN to)\n          (NP\n            (NP (NNS roles))\n            (PP (JJ such) (IN as)\n              (NP (JJ straight) (NN porn) (NN star))))))\n      (, ,)\n      (VP\n        (NP (PRP$ his) (JJ romantic) (NN relationship))\n        (PP (IN with)\n          (NP\n            (NP\n              (ADVP (CC and)\n                (RB later))\n              (NN marriage))\n            (PP (IN to)\n              (NP (NN singer) (NNP Margaret) (NNP Whiting))))))\n      (, ,)\n      (VP\n        (NP (PRP$ his) (NN activism))\n        (PP (IN in)\n          (S\n            (VP (VBG supporting)\n              (CC and)\n              (VBG promoting)\n              (NP (NNP AIDS) (NNS charities))))))\n      (CC and)\n      (VP\n        (NP (PRP$ his) (JJ later) (NN career))\n        (PP (IN as)\n          (NP\n            (NP (DT a) (JJ theatrical) (NN producer))\n            (CC and)\n            (NP (NN director))))))\n    (. .)))\n", "(ROOT\n  (S\n    (NP (DT The) (NN documentary))\n    (VP (VBD won)\n      (NP (DT a) (NNP GayVNAward))\n      (PP (IN in)\n        (NP (CD 2009)))\n      (PP (IN for)\n        (NP\n          (NP (JJS Best))\n          (NP (JJ Alternative) (NN Release)))))\n    (. .)))\n", "(ROOT\n  (S\n    (NP (NNP Wrangler))\n    (VP (VBD died)\n      (PP (IN on)\n        (NP\n          (NP (NNP April) (CD 7) (, ,) (CD 2009))\n          (PP (IN at)\n            (NP\n              (NP (DT the) (NN age))\n              (PP (IN of)\n                (NP (CD 62)))))))\n      (PP (IN due)\n        (PP (IN to)\n          (NP (NN emphysema)))))\n    (. .)))\n"], "coref": [[[0, 26, 27], [1, 0, 0], [1, 2, 2], [2, 0, 1], [3, 0, 1], [4, 0, 1]], [[2, 6, 18], [0, 16, 17], [5, 0, 0]], [[0, 8, 8], [1, 6, 6]]], "srl": [{"arguments": [[[6, 6, "V"], [0, 5, "N-ARG-A1"], [7, 27, "N-ARG-A2"]], [[19, 19, "V"], [7, 17, "N-ARG-A1"], [22, 27, "N-ARG-A0"]], [[21, 21, "V"], [7, 17, "N-ARG-A1"], [22, 27, "N-ARG-A0"]]], "frameset_ids": ["01", "01", "01"], "lemmas": ["be", "produce", "direct"], "plabel": [["ARG1", "ARG2", "ADV", "PRD", "DIS"], ["ARG0", "ARG1"], ["ARG0", "ARG1", "TMP"]], "plemma_ids": ["be.01", "produce.01", "direct.01"], "predicates": [6, 19, 21], "sentence": ["Wrangler", ":", "Anatomy", "of", "an", "Icon", "is", "a", "2008", "feature", "documentary", "film", "about", "the", "life", "of", "Jack", "Wrangler", ",", "produced", "and", "directed", "by", "Jeffrey", "Schwarz", "of", "Automat", "Pictures", "."]}, {"arguments": [[[1, 1, "V"], [0, 0, "N-ARG-A0"], [2, 3, "N-ARG-A1"], [4, 21, "N-ARGM-LOC"]], [[23, 23, "V"]], [[24, 24, "V"], [0, 0, "N-ARG-A1"], [25, 27, "N-ARG-A0"]], [[27, 27, "V"], [26, 26, "N-ARG-A0"]]], "frameset_ids": ["03", "03", "01", "01"], "lemmas": ["have", "be", "distribute", "release"], "plabel": [["ARG0", "ARG1", "LOC", "TMP"], [], ["ARG0", "ARG1"], ["ARG0", "ARG1"]], "plemma_ids": ["have.03", "be.03", "distribute.01", "release.01"], "predicates": [1, 23, 24, 27], "sentence": ["It", "had", "its", "premiere", "at", "the", "2008", "New", "York", "Lesbian", ",", "Gay", ",", "Bisexual", ",", "&", "Transgender", "Film", "Festival", "(", "Newfest", ")", "and", "is", "distributed", "by", "TLA", "Releasing", "."]}, {"arguments": [[[2, 2, "V"], [0, 1, "N-ARG-A0"], [3, 42, "N-ARG-A1"]], [[26, 26, "V"], [20, 23, "N-ARG-A1"], [24, 24, "R-ARG-A1"], [25, 25, "N-ARGM-MNR"], [27, 42, "N-ARG-A2"]], [[36, 36, "V"], [29, 34, "N-ARG-A0"], [37, 42, "N-ARG-A1"]], [[42, 42, "V"], [41, 41, "N-ARG-A1"]]], "frameset_ids": ["01", "01", "01", "02"], "lemmas": ["chronicle", "become", "achieve", "follow"], "plabel": [["ARG0", "ARG1", "MNR", "ADV", "LOC", "PRD"], ["ARG1", "ARG2", "MNR", "ADV", "TMP", "PRD", "DIS", "EXT"], ["ARG0", "ARG1", "TMP"], ["ARG1", "ARG2", "MNR", "TMP", "PRD", "ADJ"]], "plemma_ids": ["chronicle.01", "become.01", "achieve.01", "follow.02"], "predicates": [2, 26, 36, 42], "sentence": ["The", "documentary", "chronicles", "the", "life", "of", "Jack", "Wrangler", ",", "the", "professional", "name", "of", "John", "Robert", "Stillman", "in", "his", "role", "as", "a", "gay", "porn", "star", "who", "rapidly", "became", "one", "of", "the", "first", "performers", "in", "gay", "porn", "to", "achieve", "star", "status", "and", "a", "cult", "following", "."]}, {"arguments": [[[3, 3, "V"], [0, 1, "N-ARG-A0"], [2, 2, "N-ARGM-DIS"], [4, 43, "N-ARG-A1"]], [[5, 5, "V"], [4, 4, "N-ARG-A1"], [6, 12, "N-ARG-A2"]], [[29, 29, "V"], [32, 33, "N-ARG-A1"]], [[31, 31, "V"], [32, 33, "N-ARG-A1"]]], "frameset_ids": ["01", "01", "01", "02"], "lemmas": ["feature", "transition", "support", "promote"], "plabel": [["ARG0", "ARG1", "MNR", "ADV", "TMP", "PRD", "DIS"], ["ARG0", "ARG1", "ARG2", "TMP"], ["ARG0", "ARG1"], ["ARG0", "ARG1", "TMP"]], "plemma_ids": ["feature.01", "transition.01", "support.01", "promote.02"], "predicates": [3, 5, 29, 31], "sentence": ["The", "documentary", "also", "features", "his", "transitioning", "to", "roles", "such", "as", "straight", "porn", "star", ",", "his", "romantic", "relationship", "with", "and", "later", "marriage", "to", "singer", "Margaret", "Whiting", ",", "his", "activism", "in", "supporting", "and", "promoting", "AIDS", "charities", "and", "his", "later", "career", "as", "a", "theatrical", "producer", "and", "director", "."]}, {"arguments": [[[2, 2, "V"], [0, 1, "N-ARG-A0"], [3, 4, "N-ARG-A1"], [5, 6, "N-ARGM-TMP"], [7, 10, "N-ARGM-PRD"]]], "frameset_ids": ["01"], "lemmas": ["win"], "plabel": [["ARG0", "ARG1", "ARG2", "ARG3", "ARG4", "MNR", "ADV", "LOC", "TMP", "PRP", "PRD"]], "plemma_ids": ["win.01"], "predicates": [2], "sentence": ["The", "documentary", "won", "a", "GayVNAward", "in", "2009", "for", "Best", "Alternative", "Release", "."]}, {"arguments": [[[1, 1, "V"], [0, 0, "N-ARG-A1"], [2, 6, "N-ARGM-TMP"], [7, 11, "N-ARGM-TMP"], [12, 14, "N-ARGM-CAU"]]], "frameset_ids": ["01"], "lemmas": ["die"], "plabel": [["ARG0", "ARG1", "ARG2", "ARG3", "ARG4", "MNR", "ADV", "LOC", "TMP", "PRD", "DIR", "DIS", "MOD", "NEG", "CAU", "EXT", "ADJ"]], "plemma_ids": ["die.01"], "predicates": [1], "sentence": ["Wrangler", "died", "on", "April", "7", ",", "2009", "at", "the", "age", "of", "62", "due", "to", "emphysema", "."]}], "wsd": [[0, 2, "anatomy%1:04:00::"], [0, 5, "icon%1:06:00::"], [0, 6, "be%2:42:06::"], [0, 9, "feature%1:10:00::"], [0, 10, "documentary%1:10:00::"], [0, 11, "film%1:10:01::"], [0, 14, "life%1:26:02::"], [0, 19, "produce%2:39:00::"], [0, 21, "direct%2:36:00::"], [1, 1, "have%2:36:00::"], [1, 3, "premiere%1:10:00::"], [1, 23, "be%2:42:03::"], [1, 24, "distribute%2:41:00::"], [1, 27, "release%2:32:00::"], [2, 1, "documentary%1:10:00::"], [2, 2, "chronicle%2:32:00::"], [2, 4, "life%1:26:02::"], [2, 10, "professional%3:01:00::"], [2, 11, "name%1:10:00::"], [2, 18, "role%1:09:00::"], [2, 21, "gay%5:00:00:homosexual:00"], [2, 22, "porn%1:04:00::"], [2, 23, "star%1:18:02::"], [2, 25, "rapidly%4:02:00::"], [2, 26, "become%2:42:01::"], [2, 30, "first%3:00:00::"], [2, 31, "performer%1:18:00::"], [2, 33, "gay%5:00:00:homosexual:00"], [2, 34, "porn%1:04:00::"], [2, 36, "achieve%2:41:00::"], [2, 37, "star%1:18:02::"], [2, 38, "status%1:26:00::"], [2, 41, "cult%1:09:01::"], [2, 42, "follow%2:42:04::"], [3, 1, "documentary%1:10:00::"], [3, 2, "also%4:02:00::"], [3, 3, "feature%2:42:00::"], [3, 5, "transition%2:30:00::"], [3, 7, "role%1:09:00::"], [3, 8, "such%5:00:00:much:00"], [3, 10, "straight%5:00:00:heterosexual:00"], [3, 11, "porn%1:04:00::"], [3, 12, "star%1:18:02::"], [3, 15, "romantic%5:00:01:loving:00"], [3, 16, "relationship%1:26:00::"], [3, 19, "later%4:02:01::"], [3, 20, "marriage%1:26:00::"], [3, 22, "singer%1:18:00::"], [3, 27, "activism%1:09:00::"], [3, 29, "support%2:41:01::"], [3, 31, "promote%2:32:00::"], [3, 33, "charity%1:14:00::"], [3, 36, "later%5:00:00:subsequent:00"], [3, 37, "career%1:04:00::"], [3, 40, "theatrical%3:01:00::"], [3, 41, "producer%1:18:02::"], [3, 43, "director%1:18:02::"], [4, 1, "documentary%1:10:00::"], [4, 2, "win%2:40:00::"], [4, 8, "good%3:00:01::"], [4, 9, "alternative%5:00:00:unconventional:01"], [4, 10, "release%1:06:00::"], [5, 1, "die%2:30:00::"], [5, 9, "age%1:07:00::"], [5, 14, "emphysema%1:26:00::"]], "entities": [[0, 0, 0, "TITLE"], [0, 5, 5, "MISC"], [0, 8, 8, "DATE"], [0, 16, 17, "PERSON"], [0, 23, 24, "PERSON"], [0, 26, 27, "ORGANIZATION"], [1, 6, 6, "DATE"], [1, 7, 8, "STATE_OR_PROVINCE"], [1, 9, 9, "LOCATION"], [1, 26, 26, "ORGANIZATION"], [2, 6, 7, "PERSON"], [2, 13, 15, "PERSON"], [2, 22, 23, "TITLE"], [2, 27, 27, "NUMBER"], [2, 30, 30, "ORDINAL"], [2, 41, 41, "RELIGION"], [3, 11, 12, "TITLE"], [3, 22, 22, "TITLE"], [3, 23, 24, "PERSON"], [3, 32, 32, "CAUSE_OF_DEATH"], [3, 41, 41, "TITLE"], [3, 43, 43, "TITLE"], [4, 6, 6, "DATE"], [5, 0, 0, "TITLE"], [5, 3, 6, "DATE"], [5, 11, 11, "NUMBER"], [5, 14, 14, "CAUSE_OF_DEATH"]]}