{"sentences": ["Monumental Church is a former Episcopal church that stands at 1224 E. Broad Street between N. 12th and College Streets in Richmond , Virginia .\n", "Designed by architect Robert Mills , it is one of America 's earliest and most distinctive Greek Revival churches and is listed on the National Register of Historic Places , is a National Historic Landmark and is located in the Court End historic district .\n", "Monumental Church was built between 1812 and 1814 to commemorate the 72 people who died on the site in the December 26 , 1811 Richmond Theatre fire .\n", "The building consists of two parts : a crypt and a church .\n", "The crypt is located beneath the sanctuary and contains the remains of those claimed by the fire .\n", "The church is an octagonal construction of brick and Aquia sandstone with a stucco coat .\n"], "toktext": [[["Monumental", "monumental"], ["Church", "church"], ["is", "be"], ["a", "a"], ["former", "former"], ["Episcopal", "episcopal"], ["church", "church"], ["that", "that"], ["stands", "stand"], ["at", "at"], ["1224", "1224"], ["E.", "E."], ["Broad", "Broad"], ["Street", "Street"], ["between", "between"], ["N.", "N."], ["12th", "12th"], ["and", "and"], ["College", "College"], ["Streets", "Streets"], ["in", "in"], ["Richmond", "Richmond"], [",", ","], ["Virginia", "Virginia"], [".", "."]], [["Designed", "design"], ["by", "by"], ["architect", "architect"], ["Robert", "Robert"], ["Mills", "Mills"], [",", ","], ["it", "it"], ["is", "be"], ["one", "one"], ["of", "of"], ["America", "America"], ["'s", "'s"], ["earliest", "early"], ["and", "and"], ["most", "most"], ["distinctive", "distinctive"], ["Greek", "Greek"], ["Revival", "Revival"], ["churches", "church"], ["and", "and"], ["is", "be"], ["listed", "list"], ["on", "on"], ["the", "the"], ["National", "National"], ["Register", "Register"], ["of", "of"], ["Historic", "historic"], ["Places", "place"], [",", ","], ["is", "be"], ["a", "a"], ["National", "National"], ["Historic", "Historic"], ["Landmark", "Landmark"], ["and", "and"], ["is", "be"], ["located", "locate"], ["in", "in"], ["the", "the"], ["Court", "Court"], ["End", "end"], ["historic", "historic"], ["district", "district"], [".", "."]], [["Monumental", "monumental"], ["Church", "church"], ["was", "be"], ["built", "build"], ["between", "between"], ["1812", "1812"], ["and", "and"], ["1814", "1814"], ["to", "to"], ["commemorate", "commemorate"], ["the", "the"], ["72", "72"], ["people", "person"], ["who", "who"], ["died", "die"], ["on", "on"], ["the", "the"], ["site", "site"], ["in", "in"], ["the", "the"], ["December", "December"], ["26", "26"], [",", ","], ["1811", "1811"], ["Richmond", "Richmond"], ["Theatre", "Theatre"], ["fire", "fire"], [".", "."]], [["The", "the"], ["building", "building"], ["consists", "consist"], ["of", "of"], ["two", "two"], ["parts", "part"], [":", ":"], ["a", "a"], ["crypt", "crypt"], ["and", "and"], ["a", "a"], ["church", "church"], [".", "."]], [["The", "the"], ["crypt", "crypt"], ["is", "be"], ["located", "locate"], ["beneath", "beneath"], ["the", "the"], ["sanctuary", "sanctuary"], ["and", "and"], ["contains", "contain"], ["the", "the"], ["remains", "remains"], ["of", "of"], ["those", "that"], ["claimed", "claim"], ["by", "by"], ["the", "the"], ["fire", "fire"], [".", "."]], [["The", "the"], ["church", "church"], ["is", "be"], ["an", "a"], ["octagonal", "octagonal"], ["construction", "construction"], ["of", "of"], ["brick", "brick"], ["and", "and"], ["Aquia", "Aquia"], ["sandstone", "sandstone"], ["with", "with"], ["a", "a"], ["stucco", "stucco"], ["coat", "coat"], [".", "."]]], "constit": ["(ROOT\n  (S\n    (NP (JJ Monumental) (NN Church))\n    (VP (VBZ is)\n      (NP\n        (NP (DT a) (JJ former) (JJ Episcopal) (NN church))\n        (SBAR\n          (WHNP (WDT that))\n          (S\n            (VP (VBZ stands)\n              (PP (IN at)\n                (NP\n                  (NP (CD 1224) (NNP E.) (NNP Broad) (NNP Street))\n                  (PP (IN between)\n                    (NP (NNP N.)\n                      (NML (NNP 12th)\n                        (CC and)\n                        (NNP College))\n                      (NNPS Streets)))))\n              (PP (IN in)\n                (NP (NNP Richmond) (, ,) (NNP Virginia))))))))\n    (. .)))\n", "(ROOT\n  (S\n    (S\n      (VP (VBN Designed)\n        (PP (IN by)\n          (NP (NN architect) (NNP Robert) (NNP Mills)))))\n    (, ,)\n    (NP (PRP it))\n    (VP\n      (VP (VBZ is)\n        (NP\n          (NP (CD one))\n          (PP (IN of)\n            (NP\n              (ADJP\n                (ADJP\n                  (NP (NNP America) (POS 's))\n                  (JJS earliest))\n                (CC and)\n                (ADJP (RBS most) (JJ distinctive))\n                (NP (NNP Greek) (NNP Revival)))\n              (NNS churches)))))\n      (CC and)\n      (VP (VBZ is)\n        (VP (VBN listed)\n          (PP (IN on)\n            (NP\n              (NP (DT the) (NNP National) (NNP Register))\n              (PP (IN of)\n                (NP (JJ Historic) (NNS Places)))))))\n      (, ,)\n      (VP (VBZ is)\n        (NP (DT a) (NNP National) (NNP Historic) (NNP Landmark)))\n      (CC and)\n      (VP (VBZ is)\n        (VP (VBN located)\n          (PP (IN in)\n            (NP (DT the)\n              (NML (NNP Court) (NN End))\n              (JJ historic) (NN district))))))\n    (. .)))\n", "(ROOT\n  (S\n    (NP (JJ Monumental) (NN Church))\n    (VP (VBD was)\n      (VP (VBN built)\n        (PP (IN between)\n          (NP (CD 1812)\n            (CC and)\n            (CD 1814)))\n        (PP (IN to)\n          (NP\n            (NML\n              (S\n                (VP (VB commemorate)\n                  (NP\n                    (NP (DT the) (CD 72) (NNS people))\n                    (SBAR\n                      (WHNP (WP who))\n                      (S\n                        (VP (VBD died)\n                          (PP (IN on)\n                            (NP\n                              (NP (DT the) (NN site))\n                              (PP (IN in)\n                                (NP (DT the) (NNP December)\n                                  (NML (CD 26) (, ,) (CD 1811))\n                                  (NNP Richmond) (NNP Theatre))))))))))))\n            (NN fire)))))\n    (. .)))\n", "(ROOT\n  (S\n    (NP (DT The) (NN building))\n    (VP (VBZ consists)\n      (PP (IN of)\n        (NP (CD two) (NNS parts)))\n      (: :)\n      (NP\n        (NP (DT a) (NN crypt))\n        (CC and)\n        (NP (DT a) (NN church))))\n    (. .)))\n", "(ROOT\n  (S\n    (NP (DT The) (NN crypt))\n    (VP\n      (VP (VBZ is)\n        (VP (VBN located)\n          (PP (IN beneath)\n            (NP (DT the) (NN sanctuary)))))\n      (CC and)\n      (VP (VBZ contains)\n        (NP\n          (NP (DT the) (NNS remains))\n          (PP (IN of)\n            (NP\n              (NP (DT those))\n              (VP (VBN claimed)\n                (PP (IN by)\n                  (NP (DT the) (NN fire)))))))))\n    (. .)))\n", "(ROOT\n  (S\n    (NP (DT The) (NN church))\n    (VP (VBZ is)\n      (NP\n        (NP (DT an) (JJ octagonal) (NN construction))\n        (PP (IN of)\n          (NP\n            (NP\n              (NML\n                (NML (NN brick))\n                (CC and)\n                (NML (NNP Aquia)))\n              (NN sandstone))\n            (PP (IN with)\n              (NP (DT a) (NN stucco) (NN coat)))))))\n    (. .)))\n"], "coref": [[[3, 7, 8], [4, 0, 1]]], "srl": [{"arguments": [[[2, 2, "V"], [0, 1, "N-ARG-A1"], [3, 23, "N-ARG-A2"]], [[8, 8, "V"], [3, 6, "N-ARG-A1"], [7, 7, "R-ARG-A1"], [9, 19, "N-ARG-A2"], [20, 23, "N-ARGM-LOC"]]], "frameset_ids": ["01", "01"], "lemmas": ["be", "stand"], "plabel": [["ARG1", "ARG2", "ADV"], ["ARG0", "ARG1", "ARG2", "LOC"]], "plemma_ids": ["be.01", "stand.01"], "predicates": [2, 8], "sentence": ["Monumental", "Church", "is", "a", "former", "Episcopal", "church", "that", "stands", "at", "1224", "E.", "Broad", "Street", "between", "N.", "12th", "and", "College", "Streets", "in", "Richmond", ",", "Virginia", "."]}, {"arguments": [[[0, 0, "V"], [1, 4, "N-ARG-A0"], [6, 6, "N-ARG-A1"]], [[7, 7, "V"], [0, 4, "R-ARG-A1"], [6, 6, "N-ARG-A1"], [8, 18, "N-ARG-A2"]], [[20, 20, "V"]], [[21, 21, "V"], [6, 6, "N-ARG-A1"], [22, 28, "N-ARG-A2"]], [[30, 30, "V"], [0, 4, "R-ARG-A1"], [6, 6, "N-ARG-A1"], [31, 34, "N-ARG-A2"]], [[36, 36, "V"]], [[37, 37, "V"], [0, 4, "N-ARGM-ADV"], [6, 6, "N-ARG-A1"], [38, 43, "N-ARGM-LOC"]]], "frameset_ids": ["01", "01", "03", "01", "01", "03", "01"], "lemmas": ["design", "be", "be", "list", "be", "be", "locate"], "plabel": [["ARG0", "ARG1", "TMP"], ["ARG1", "ARG2", "ADV", "TMP", "PRD", "CAU"], ["ARG1", "ARG2"], ["ARG1", "ARG2", "ADV", "TMP", "DIS"], ["ARG1", "ARG2", "ADV", "PRD"], ["ARG1"], ["ARG1", "ARG2", "ADV", "LOC", "TMP", "PRD", "DIS"]], "plemma_ids": ["design.01", "be.01", "be.03", "list.01", "be.01", "be.03", "locate.01"], "predicates": [0, 7, 20, 21, 30, 36, 37], "sentence": ["Designed", "by", "architect", "Robert", "Mills", ",", "it", "is", "one", "of", "America", "'s", "earliest", "and", "most", "distinctive", "Greek", "Revival", "churches", "and", "is", "listed", "on", "the", "National", "Register", "of", "Historic", "Places", ",", "is", "a", "National", "Historic", "Landmark", "and", "is", "located", "in", "the", "Court", "End", "historic", "district", "."]}, {"arguments": [[[2, 2, "V"]], [[3, 3, "V"], [0, 1, "N-ARG-A1"], [4, 7, "N-ARGM-TMP"], [8, 26, "N-ARGM-PRP"]], [[9, 9, "V"], [10, 26, "N-ARG-A1"]], [[14, 14, "V"], [10, 12, "N-ARG-A1"], [13, 13, "R-ARG-A1"], [15, 17, "N-ARGM-LOC"], [18, 26, "N-ARGM-LOC"]]], "frameset_ids": ["03", "01", "01", "01"], "lemmas": ["be", "build", "commemorate", "die"], "plabel": [[], ["ARG0", "ARG1", "ARG2", "ARG3", "ARG4", "MNR", "ADV", "LOC", "TMP", "PRP", "PRD", "DIR", "DIS", "MOD", "NEG", "CAU", "EXT", "GOL", "COM", "PNC"], ["ARG0", "ARG1", "ARG2", "TMP"], ["ARG0", "ARG1", "MNR", "ADV", "LOC", "TMP", "PRP", "PRD", "DIS", "MOD"]], "plemma_ids": ["be.03", "build.01", "commemorate.01", "die.01"], "predicates": [2, 3, 9, 14], "sentence": ["Monumental", "Church", "was", "built", "between", "1812", "and", "1814", "to", "commemorate", "the", "72", "people", "who", "died", "on", "the", "site", "in", "the", "December", "26", ",", "1811", "Richmond", "Theatre", "fire", "."]}, {"arguments": [[[2, 2, "V"], [0, 1, "N-ARG-A1"], [3, 11, "N-ARG-A2"]]], "frameset_ids": ["01"], "lemmas": ["consist"], "plabel": [["ARG1", "ARG2", "ADV", "TMP", "PRD"]], "plemma_ids": ["consist.01"], "predicates": [2], "sentence": ["The", "building", "consists", "of", "two", "parts", ":", "a", "crypt", "and", "a", "church", "."]}, {"arguments": [[[2, 2, "V"]], [[3, 3, "V"], [0, 1, "N-ARG-A1"], [4, 6, "N-ARGM-LOC"]], [[8, 8, "V"], [0, 1, "N-ARG-A0"], [9, 16, "N-ARG-A1"]], [[13, 13, "V"], [12, 12, "N-ARG-A1"], [14, 16, "N-ARGM-MNR"]]], "frameset_ids": ["03", "01", "01", "02"], "lemmas": ["be", "locate", "contain", "claim"], "plabel": [["ARG1", "ARG2"], ["ARG0", "ARG1", "MNR", "ADV", "LOC", "TMP", "PRD", "DIS"], ["ARG0", "ARG1"], ["ARG0", "ARG1", "MNR", "ADV", "TMP"]], "plemma_ids": ["be.03", "locate.01", "contain.01", "claim.02"], "predicates": [2, 3, 8, 13], "sentence": ["The", "crypt", "is", "located", "beneath", "the", "sanctuary", "and", "contains", "the", "remains", "of", "those", "claimed", "by", "the", "fire", "."]}, {"arguments": [[[2, 2, "V"], [0, 1, "N-ARG-A1"], [3, 14, "N-ARG-A2"]]], "frameset_ids": ["01"], "lemmas": ["be"], "plabel": [["ARG1", "ARG2", "ADV", "PRD"]], "plemma_ids": ["be.01"], "predicates": [2], "sentence": ["The", "church", "is", "an", "octagonal", "construction", "of", "brick", "and", "Aquia", "sandstone", "with", "a", "stucco", "coat", "."]}], "wsd": [[0, 0, "monumental%3:01:00::"], [0, 1, "church%1:06:00::"], [0, 2, "be%2:42:06::"], [0, 4, "former%5:00:01:past:00"], [0, 5, "episcopal%3:01:01::"], [0, 6, "church%1:06:00::"], [0, 8, "stand%2:35:00::"], [1, 0, "design%2:36:00::"], [1, 2, "architect%1:18:00::"], [1, 7, "be%2:42:03::"], [1, 12, "early%5:00:00:past:00"], [1, 14, "most%4:02:00::"], [1, 15, "distinctive%5:00:00:characteristic:00"], [1, 18, "church%1:06:00::"], [1, 20, "be%2:42:03::"], [1, 21, "list%2:41:00::"], [1, 27, "historic%5:00:00:important:00"], [1, 28, "place%1:15:00::"], [1, 30, "be%2:42:03::"], [1, 36, "be%2:42:05::"], [1, 37, "locate%2:42:00::"], [1, 41, "end%1:15:00::"], [1, 42, "historic%5:00:00:important:00"], [1, 43, "district%1:15:00::"], [2, 0, "monumental%3:01:00::"], [2, 1, "church%1:06:00::"], [2, 2, "be%2:42:03::"], [2, 3, "build%2:36:00::"], [2, 9, "commemorate%2:31:01::"], [2, 12, "person%1:03:00::"], [2, 14, "die%2:30:00::"], [2, 17, "site%1:15:00::"], [2, 26, "fire%1:11:00::"], [3, 1, "building%1:06:00::"], [3, 2, "consist%2:42:01::"], [3, 5, "part%1:06:00::"], [3, 8, "crypt%1:06:00::"], [3, 11, "church%1:06:00::"], [4, 1, "crypt%1:06:00::"], [4, 2, "be%2:42:03::"], [4, 3, "locate%2:42:00::"], [4, 6, "sanctuary%1:06:00::"], [4, 8, "contain%2:42:13::"], [4, 10, "remains%1:08:00::"], [4, 13, "claim%2:32:01::"], [4, 16, "fire%1:11:00::"], [5, 1, "church%1:06:00::"], [5, 2, "be%2:42:03::"], [5, 4, "octagonal%3:01:00::"], [5, 5, "construction%1:06:00::"], [5, 7, "brick%1:06:00::"], [5, 10, "sandstone%1:27:00::"], [5, 13, "stucco%1:27:00::"], [5, 14, "coat%1:06:01::"]], "entities": [[0, 5, 6, "RELIGION"], [0, 10, 10, "DATE"], [0, 16, 16, "ORDINAL"], [0, 21, 21, "CITY"], [0, 23, 23, "STATE_OR_PROVINCE"], [1, 2, 2, "TITLE"], [1, 3, 4, "PERSON"], [1, 8, 8, "NUMBER"], [1, 10, 10, "COUNTRY"], [1, 16, 16, "NATIONALITY"], [1, 32, 34, "MISC"], [1, 40, 41, "MISC"], [2, 5, 7, "DATE"], [2, 11, 11, "NUMBER"], [2, 20, 23, "DATE"], [2, 24, 24, "CITY"], [2, 25, 25, "LOCATION"], [2, 26, 26, "CAUSE_OF_DEATH"], [3, 4, 4, "NUMBER"], [4, 16, 16, "CAUSE_OF_DEATH"]]}